funtool/__init__.py
funtool/adaptor.py
funtool/analysis.py
funtool/analysis_selector.py
funtool/api.py
funtool/group.py
funtool/group_measure.py
funtool/grouping_selector.py
funtool/logger.py
funtool/reporter.py
funtool/state.py
funtool/state_collection.py
funtool/state_measure.py
funtool/lib/__init__.py
funtool/lib/config_parse.py
funtool/lib/general.py
funtool-0.0.87.dist-info/DESCRIPTION.rst
funtool-0.0.87.dist-info/METADATA
funtool-0.0.87.dist-info/metadata.json
funtool-0.0.87.dist-info/RECORD
funtool-0.0.87.dist-info/top_level.txt
funtool-0.0.87.dist-info/WHEEL
