Metadata-Version: 2.0
Name: funtool
Version: 0.0.87
Summary: FUN Tool engine: Used process an analysis
Home-page: https://github.com/pjanis/funtool
Author: Active Learning Lab
Author-email: pjanisiewicz@gmail.com
License: MIT
Platform: UNKNOWN
Classifier: Development Status :: 3 - Alpha
Classifier: Intended Audience :: Developers
Classifier: License :: OSI Approved :: MIT License
Classifier: Programming Language :: Python :: 3
Classifier: Programming Language :: Python :: 3.2
Classifier: Programming Language :: Python :: 3.3
Classifier: Programming Language :: Python :: 3.4
Requires-Dist: PyYAML
